pyimagewatch/__init__.py
pyimagewatch/pyimagewatch.py
pyimagewatch-0.1.1.dist-info/LICENSE
pyimagewatch-0.1.1.dist-info/METADATA
pyimagewatch-0.1.1.dist-info/WHEEL
pyimagewatch-0.1.1.dist-info/top_level.txt
pyimagewatch-0.1.1.dist-info/RECORD
